setup.py
src/csv_ccbv/__init__.py
src/csv_ccbv/views.py
src/django_csv_ccbv.egg-info/PKG-INFO
src/django_csv_ccbv.egg-info/SOURCES.txt
src/django_csv_ccbv.egg-info/dependency_links.txt
src/django_csv_ccbv.egg-info/top_level.txt