Metadata-Version: 1.1
Name: django-csv-ccbv
Version: 0.1
Summary: Easy to fetch a CSV on a CCBV
Home-page: https://github.com/aRkadeFR/django-common-templatetags
Author: aRkadeFR
Author-email: contact@arkade.info
License: UNKNOWN
Platform: UNKNOWN
Classifier: Framework :: Django
